lichesspy/__init__.py
lichesspy/api.py
lichesspy/auth.py
lichesspy/format.py
lichesspy/pgn.py
lichesspy-6.0.5.dist-info/LICENSE
lichesspy-6.0.5.dist-info/METADATA
lichesspy-6.0.5.dist-info/WHEEL
lichesspy-6.0.5.dist-info/top_level.txt
lichesspy-6.0.5.dist-info/RECORD
