Metadata-Version: 2.1
Name: lichesspy
Version: 6.0.5
Summary: Python wrapper for lichess
Home-page: https://github.com/eskopp/lichesspy
Author: eskopp
Author-email: skopp.erik+lichesspy@gmail.com
License: MIT
Classifier: Programming Language :: Python :: 3
Classifier: License :: OSI Approved :: MIT License
Classifier: Operating System :: OS Independent
Requires-Python: >=3.10
License-File: LICENSE
Requires-Dist: requests ==2.32.3
Requires-Dist: six ==1.16.0
Requires-Dist: chess ==1.11.0
